.DS_Store
pykids/.DS_Store
pykids/__init__.py
pykids/demo/__init__.py
pykids/demo/hello.py
pykids-0.0.dist-info/METADATA
pykids-0.0.dist-info/WHEEL
pykids-0.0.dist-info/top_level.txt
pykids-0.0.dist-info/RECORD
