Metadata-Version: 2.1
Name: pykids
Version: 0.0
Summary: This is a kid's python library.
Home-page: https://pymilk.com/
Author: pykids
Author-email: vaporzfy@sina.com
License: GPL2
Platform: UNKNOWN
